src/__init__.py
src/__main__.py
src/server.py
src/tools/__init__.py
src/tools/email_template_generator.py
src/tools/nosto_snippet_generator.py
nosto_email_widgets_mcp-0.1.0.dist-info/METADATA
nosto_email_widgets_mcp-0.1.0.dist-info/WHEEL
nosto_email_widgets_mcp-0.1.0.dist-info/entry_points.txt
nosto_email_widgets_mcp-0.1.0.dist-info/RECORD
