Metadata-Version: 2.4
Name: nosto-email-widgets-mcp
Version: 0.1.0
Summary: MCP Server for Nosto Email Widgets with FastMCP
Author-email: Nosto Team <team@nosto.com>
Requires-Python: >=3.10
Requires-Dist: fastapi>=0.104.0
Requires-Dist: fastmcp>=0.1.0
Requires-Dist: jinja2>=3.1.0
Requires-Dist: mcp>=1.0.0
Requires-Dist: pydantic>=2.0.0
Requires-Dist: starlette>=0.27.0
Requires-Dist: uvicorn>=0.24.0
Provides-Extra: dev
Requires-Dist: black>=23.0.0; extra == 'dev'
Requires-Dist: flake8>=6.0.0; extra == 'dev'
Requires-Dist: isort>=5.12.0; extra == 'dev'
Requires-Dist: mypy>=1.0.0; extra == 'dev'
Requires-Dist: pytest-asyncio>=0.21.0; extra == 'dev'
Requires-Dist: pytest>=7.0.0; extra == 'dev'
